LICENSE.txt
MANIFEST.in
README.rst
setup.cfg
setup.py
openet/__init__.py
openet.egg-info/PKG-INFO
openet.egg-info/SOURCES.txt
openet.egg-info/dependency_links.txt
openet.egg-info/not-zip-safe
openet.egg-info/requires.txt
openet.egg-info/top_level.txt
openet/core/__init__.py
openet/core/api.py
openet/core/common.py
openet/core/interp.py
openet/core/utils.py
openet/core/tests/conftest.py
openet/core/tests/test_common.py
openet/core/tests/test_interp.py
openet/core/tests/test_utils.py