Metadata-Version: 1.1
Name: openet
Version: 0.0.5
Summary: OpenET Core Components
Home-page: https://github.com/Open-ET/openet-core-beta
Author: Charles Morton
Author-email: charles.morton@dri.edu
License: Apache
Download-URL: https://github.com/Open-ET/openet-core-beta/archive/v0.0.5.tar.gz
Keywords: OpenET Evapotranspiration Earth Engine
Platform: UNKNOWN
Classifier: License :: OSI Approved :: Apache Software License
Classifier: Programming Language :: Python :: 3.6
